odoo/addons/account_portal_invoice_search/README.rst
odoo/addons/account_portal_invoice_search/__init__.py
odoo/addons/account_portal_invoice_search/__manifest__.py
odoo/addons/account_portal_invoice_search/controllers/__init__.py
odoo/addons/account_portal_invoice_search/controllers/portal.py
odoo/addons/account_portal_invoice_search/i18n/account_portal_invoice_search.pot
odoo/addons/account_portal_invoice_search/i18n/es.po
odoo/addons/account_portal_invoice_search/models/__init__.py
odoo/addons/account_portal_invoice_search/models/account_move.py
odoo/addons/account_portal_invoice_search/readme/CONTRIBUTORS.rst
odoo/addons/account_portal_invoice_search/readme/DESCRIPTION.rst
odoo/addons/account_portal_invoice_search/readme/USAGE.rst
odoo/addons/account_portal_invoice_search/static/description/icon.png
odoo/addons/account_portal_invoice_search/static/description/index.html
odoo13_addon_account_portal_invoice_search-13.0.1.0.1.dist-info/METADATA
odoo13_addon_account_portal_invoice_search-13.0.1.0.1.dist-info/WHEEL
odoo13_addon_account_portal_invoice_search-13.0.1.0.1.dist-info/top_level.txt
odoo13_addon_account_portal_invoice_search-13.0.1.0.1.dist-info/RECORD
